mmng_ui/__init__.py
mmng_ui/_version.py
mmng_ui/pocsag.py
mmng_ui/pocsag.tcss
mmng_ui/reader.py
mmng_ui-1.3.1.dist-info/METADATA
mmng_ui-1.3.1.dist-info/WHEEL
mmng_ui-1.3.1.dist-info/entry_points.txt
mmng_ui-1.3.1.dist-info/licenses/LICENSE
mmng_ui-1.3.1.dist-info/RECORD
