Metadata-Version: 2.4
Name: mmng-ui
Version: 1.3.1
Summary: The textual user interface to multimon-ng.
Project-URL: Homepage, https://github.com/lingfish/mmng-ui
Project-URL: Issues, https://github.com/lingfish/mmng-ui/issues
Author-email: Jason Lingohr <jason@lucid.net.au>
License-File: LICENSE
Classifier: License :: OSI Approved :: GNU General Public License v3 or later (GPLv3+)
Classifier: Operating System :: OS Independent
Classifier: Programming Language :: Python :: 3
Requires-Python: >=3.10
Requires-Dist: click==8.3.0
Requires-Dist: moment==0.12.1
Requires-Dist: rich==14.2.0
Requires-Dist: textual==6.3.0
Provides-Extra: web
Requires-Dist: textual-serve==1.1.2; extra == 'web'
